tests/__init__.py
tests/test_algorithms.py
tests/utils.py
wfst/__init__.py
wfst/_wfst.py
wfst/cli.py
wfst/io.py
wfst/algo/__init__.py
wfst/algo/_algo.py
wfst/algo/_nbest.py
wfst-0.1.1.dist-info/LICENCE-APACHE
wfst-0.1.1.dist-info/LICENCE-MIT
wfst-0.1.1.dist-info/METADATA
wfst-0.1.1.dist-info/WHEEL
wfst-0.1.1.dist-info/entry_points.txt
wfst-0.1.1.dist-info/top_level.txt
wfst-0.1.1.dist-info/RECORD
