Metadata-Version: 2.1
Name: wfst
Version: 0.1.1
Summary: Weighted Finite State Transducers
Home-page: https://github.com/demitasse/wfstpy
Author: Daniel van Niekerk
Author-email: dvn.demitasse@gmail.com
License: Apache/MIT
Requires-Python: >=3
License-File: LICENCE-APACHE
License-File: LICENCE-MIT
